{
  "id": "record-session-wrapper",
  "name": "record-session-wrapper",
  "title": "One-shot journal recording without placeholders",
  "description": "add_session.py (Trellis-owned) hardcodes '(Add test results)' and '(see git log)' placeholders and auto-commits them; the pack's own preflight then rejects them, forcing a manual fill-and-amend dance after every session (6x this week, 2 near-misses incl. wrong hashes pushed). Ship scripts/sd-ai-command-pack-record-session.py: composes the full entry (Main Changes via --content-file, commit subjects resolved from git with fail-fast on unknown hashes, Testing from --test flags), patches the just-written entry, verifies zero placeholders, and commits. Update the sd-finish-work skill to use it. 0.5.16 + fleet refresh.",
  "status": "in_progress",
  "dev_type": null,
  "scope": null,
  "package": null,
  "priority": "P2",
  "creator": "sdelmas",
  "assignee": "sdelmas",
  "createdAt": "2026-07-04",
  "completedAt": null,
  "branch": null,
  "base_branch": "main",
  "worktree_path": null,
  "commit": null,
  "pr_url": null,
  "subtasks": [],
  "children": [],
  "parent": null,
  "relatedFiles": [],
  "notes": "",
  "meta": {}
}