{
  "id": "housekeeping-recorder-robustness",
  "name": "housekeeping-recorder-robustness",
  "title": "Robustness fixes for housekeeping, recorder, learnings, and KB scripts",
  "description": "Fail-open clean-tree check, remote arg hardening, null default branch, recorder status parsing, learnings AttributeError and marker injection, KB exit 0 on conflicts.",
  "status": "completed",
  "dev_type": null,
  "scope": null,
  "package": null,
  "priority": "P2",
  "creator": "sdelmas",
  "assignee": "sdelmas",
  "createdAt": "2026-07-06",
  "completedAt": "2026-07-08",
  "branch": null,
  "base_branch": "main",
  "worktree_path": null,
  "commit": null,
  "pr_url": null,
  "subtasks": [],
  "children": [],
  "parent": null,
  "relatedFiles": [],
  "notes": "",
  "meta": {}
}