{
  "id": "measure-scripts-coverage",
  "name": "measure-scripts-coverage",
  "title": "Measure coverage for shipped scripts Python helpers",
  "description": "About 3.8k lines of scripts/*.py have behavioral tests but no measured coverage number.",
  "status": "completed",
  "dev_type": null,
  "scope": null,
  "package": null,
  "priority": "P2",
  "creator": "sdelmas",
  "assignee": "sdelmas",
  "createdAt": "2026-07-06",
  "completedAt": "2026-07-08",
  "branch": null,
  "base_branch": "main",
  "worktree_path": null,
  "commit": null,
  "pr_url": null,
  "subtasks": [],
  "children": [],
  "parent": null,
  "relatedFiles": [],
  "notes": "",
  "meta": {}
}